macwinnie_atlassianbrowse/Atlassian.py
macwinnie_atlassianbrowse/__init__.py
macwinnie_atlassianbrowse-0.0.3.dist-info/LICENSE
macwinnie_atlassianbrowse-0.0.3.dist-info/METADATA
macwinnie_atlassianbrowse-0.0.3.dist-info/WHEEL
macwinnie_atlassianbrowse-0.0.3.dist-info/top_level.txt
macwinnie_atlassianbrowse-0.0.3.dist-info/RECORD
