Metadata-Version: 2.1
Name: macwinnie-atlassianbrowse
Version: 0.0.3
Summary: Selenium assisted implementation to execute actions on Atlassian tools.
Home-page: https://github.com/macwinnie/python-atlassian-browse
Author: macwinnie
Author-email: dev@macwinnie.me
License: AGPL-3.0-or-later
Classifier: Programming Language :: Python :: 3
Classifier: License :: OSI Approved :: GNU Affero General Public License v3 or later (AGPLv3+)
Classifier: Operating System :: OS Independent
Requires-Python: >=3.10
License-File: LICENSE
Requires-Dist: macwinnie-pyhelpers
Requires-Dist: pandas
Requires-Dist: args
Requires-Dist: requests
Requires-Dist: selenium
Requires-Dist: beautifulsoup4
